__init__.py
__version__.py
api.py
data_classes/data_class.py
data_classes/company/company.py
data_classes/company/wage_tax.py
data_classes/company/wage_tax_xml.py
data_classes/debtor/absence_verzuim.py
data_classes/debtor/address.py
data_classes/debtor/bank_account.py
data_classes/debtor/contact_info.py
data_classes/debtor/debtor.py
data_classes/debtor/department.py
data_classes/debtor/function.py
data_classes/debtor/labour_agreement_settings.py
data_classes/debtor/manager.py
data_classes/debtor/service_level.py
data_classes/debtor/tag.py
data_classes/debtor/webhook.py
data_classes/employee/employee.py
data_classes/utils/xml.py
exceptions/DefaultLoginFailure.py
exceptions/InvalidAuthentication.py
exceptions/InvalidDomain.py
exceptions/InvalidEmailPassword.py
exceptions/MissingParams.py
exceptions/MultipleEnvironments.py
exceptions/UnauthorizedAccess.py
service/company_service.py
service/debtor_service.py
service/employee_service.py
service/service.py
service/sso_service.py
utils/find_empty_params.py
utils/nmbrs_exception_handler.py
utils/return_list.py
nmbrs_soap_api-0.0.300.dist-info/LICENSE
nmbrs_soap_api-0.0.300.dist-info/METADATA
nmbrs_soap_api-0.0.300.dist-info/NOTICE
nmbrs_soap_api-0.0.300.dist-info/WHEEL
nmbrs_soap_api-0.0.300.dist-info/top_level.txt
nmbrs_soap_api-0.0.300.dist-info/RECORD
